pyqo/__init__.py
pyqo/_json.py
pyqo/_printer.py
pyqo/_srl.py
pyqo/_webbrowser.py
pyqo/ant.py
pyqo/c_.py
pyqo/d.py
pyqo/define.py
pyqo/f.py
pyqo/i.py
pyqo/rand.py
pyqo/say.py
pyqo/syn.py
pyqo/v.py
pyqo/yget.py
pyqo/data/a.json
pyqo/data/c.json
pyqo/data/config.json
pyqo/data/f.json
pyqo-0.0.7.data/scripts/c
pyqo-0.0.7.data/scripts/c.bat
pyqo-0.0.7.dist-info/LICENSE.md
pyqo-0.0.7.dist-info/METADATA
pyqo-0.0.7.dist-info/WHEEL
pyqo-0.0.7.dist-info/entry_points.txt
pyqo-0.0.7.dist-info/top_level.txt
pyqo-0.0.7.dist-info/RECORD
