Metadata-Version: 2.1
Name: pyqo
Version: 0.0.7
Summary: Useful collection of command line scripts.
Home-page: https://github.com/Whenti/pyqo
Author: Quentin LÉVÊQUE
Author-email: qleveque@hotmail.com
License: Apache License
Keywords: pip requirements imports
Platform: UNKNOWN
Classifier: License :: OSI Approved :: MIT License
Classifier: Programming Language :: Python :: 3.6
Requires-Dist: pyttsx3 (>=2.7)
Requires-Dist: setuptools (>=39.0.1)
Requires-Dist: pytube (>=9.4.0)
Requires-Dist: Click (>=7.0)
Requires-Dist: requests (>=2.18.4)
Requires-Dist: beautifulsoup4 (>=4.7.1)
